<?xml version="1.0" encoding="utf-8"?>
<!DOCTYPE hibernate-mapping PUBLIC "-//Hibernate/Hibernate Mapping DTD 3.0//EN"
"http://hibernate.sourceforge.net/hibernate-mapping-3.0.dtd">

<hibernate-mapping>

   <!-- <class name="com.sam.entity.User" table="user" catalog="library">
        <id name="id" type="java.lang.Integer">
            <column name="id" />
            <generator class="increment" />
        </id>
        <property name="username" type="java.lang.String">
            <column name="username" length="50" />
        </property>
        <property name="account" type="java.lang.String">
            <column name="account" length="50" />
        </property>
        <property name="address" type="java.lang.String">
            <column name="address" length="50" />
        </property>
    </class>
    
    <class name="com.sam.entity.Person" table="person" catalog="samlog">
        <id name="id" type="java.lang.Integer">
            <column name="id" />
            <generator class="increment" />
        </id>
        <property name="name" type="java.lang.String">
            <column name="name" length="50" />
        </property>
        <property name="age" type="java.lang.Integer">
            <column name="age" length="50" />
        </property>
    </class> -->
    
</hibernate-mapping>
